chiwassu
