Metadata-Version: 1.0
Name: chiwassu
Version: 0.0.2
Summary: for pypi practice
Home-page: UNKNOWN
Author: sotaro takeshtia
Author-email: oh.sore.sore.soutarou@gmail.com
License: MIT
Keywords: japanese
Platform: UNKNOWN
